ssm_jsonrepair/jsonrepair.py
ssm_jsonrepair/stringutils.py
ssm_jsonrepair-3.8.2.dist-info/METADATA
ssm_jsonrepair-3.8.2.dist-info/WHEEL
ssm_jsonrepair-3.8.2.dist-info/licenses/LICENSE.txt
ssm_jsonrepair-3.8.2.dist-info/RECORD
