Metadata-Version: 2.3
Name: ssm_jsonrepair
Version: 3.8.2
Summary: JSON repair can solve multiple problems in json
Project-URL: Homepage, https://github.com/SelectedSolutionManagement/jsonrepair
Project-URL: Issues, https://github.com/SelectedSolutionManagement/jsonrepair/issues
Author-email: "Selected Solution Mangement Ltd." <info@ssm.hu>
License-File: LICENSE.txt
Classifier: License :: OSI Approved :: ISC License (ISCL)
Classifier: Operating System :: OS Independent
Classifier: Programming Language :: Python :: 3
Requires-Python: >=3.8
